[
    {
        "videoUrl": "https://www.youtube.com/watch?v=_OY-qb5bLJ0",
        "videoTitle": "Godlike Splitgate Gameplay",
        "videoImg": "https://images2.minutemediacdn.com/image/upload/c_fill,w_720,ar_16:9,f_auto,q_auto,g_auto/shape/cover/sport/dataimagejpegbase649j4AAQSkZJRgABAQAAAQABAAD2wBDAA-f07f32f9a31bf241f8b81410ffba6cb2.jpg"
    },
    {
        "videoUrl": "https://www.youtube.com/watch?v=njB5daMe-RE",
        "videoTitle": "Beginner Tips and Tricks",
        "videoImg": "https://game.intel.com/assets/giveaways/dtnBCTV1m7ay5DjGNZqKYX/poster_aU4tuYx2vQTwspvFv7JR3b.jpg"
    },
    {
        "videoUrl": "https://www.youtube.com/watch?v=6YAY0UFXJxE&t=18s",
        "videoTitle": "IGN Splitgate Arena Warfare",
        "videoImg": "https://pbs.twimg.com/profile_images/1565420514105081856/mK6SVkge_400x400.jpg"
    },
    {
        "videoUrl": "https://www.youtube.com/watch?v=sB0ul27dEEU",
        "videoTitle": "50 Tips",
        "videoImg": "https://m.media-amazon.com/images/G/01/sm/Splitgate/s02_d03/Hero_1x.jpg"
    },
    {
        "videoUrl": "https://www.youtube.com/watch?v=3b44SWmMcbU",
        "videoTitle": "Advanced Tips and Tricks from Pros",
        "videoImg": "https://i.gadgets360cdn.com/products/large/62608ed542ff11766ee84538-20220322-T1-Website-Team-Thumbnails-1500x2000-Splitgate-1000x1333-1653651596.jpg?downsize=*:360"
    },
    {
        "videoUrl": "https://www.youtube.com/watch?v=6EvZF2m546k",
        "videoTitle": "Halo Infinite vs Splitgate",
        "videoImg": "https://thelazy.media/wp-content/uploads/2021/08/Splitgate-Portals-2000x1270-1.jpg"
    }
]